LICENSE
MANIFEST.in
README.md
requirements.txt
requirements_dev.txt
setup.cfg
setup.py
glow_tts/__init__.py
glow_tts/attentions.py
glow_tts/checkpoint.py
glow_tts/config.py
glow_tts/layers.py
glow_tts/models.py
glow_tts/utils.py
hifi_gan/__init__.py
hifi_gan/checkpoint.py
hifi_gan/config.py
hifi_gan/models.py
hifi_gan/utils.py
larynx/VERSION
larynx/VOCODERS
larynx/VOICES
larynx/__init__.py
larynx/__main__.py
larynx/audio.py
larynx/constants.py
larynx/glow_tts.py
larynx/griffin_lim.py
larynx/hifi_gan.py
larynx/py.typed
larynx/server.py
larynx/utils.py
larynx/wavfile.py
larynx.egg-info/PKG-INFO
larynx.egg-info/SOURCES.txt
larynx.egg-info/dependency_links.txt
larynx.egg-info/entry_points.txt
larynx.egg-info/requires.txt
larynx.egg-info/top_level.txt
larynx/css/bootstrap.min.css
larynx/templates/index.html
larynx/wav/alveolar_approximant.wav
larynx/wav/alveolar_ejective_fricative.wav
larynx/wav/alveolar_ejective_plosive.wav
larynx/wav/alveolar_lateral_approximant.wav
larynx/wav/alveolar_lateral_click.wav
larynx/wav/alveolar_lateral_flap.wav
larynx/wav/alveolar_nasal.wav
larynx/wav/alveolar_tap.wav
larynx/wav/alveolar_trill.wav
larynx/wav/bilabial_click.wav
larynx/wav/bilabial_ejective_plosive.wav
larynx/wav/bilabial_nasal.wav
larynx/wav/bilabial_trill.wav
larynx/wav/close-mid_back_rounded_vowel.wav
larynx/wav/close-mid_back_unrounded_vowel.wav
larynx/wav/close-mid_central_rounded_vowel.wav
larynx/wav/close-mid_central_unrounded_vowel.wav
larynx/wav/close-mid_front_rounded_vowel.wav
larynx/wav/close-mid_front_unrounded_vowel.wav
larynx/wav/close_back_rounded_vowel.wav
larynx/wav/close_back_unrounded_vowel.wav
larynx/wav/close_central_rounded_vowel.wav
larynx/wav/close_central_unrounded_vowel.wav
larynx/wav/close_front_rounded_vowel.wav
larynx/wav/close_front_unrounded_vowel.wav
larynx/wav/dental_click.wav
larynx/wav/glottal_plosive.wav
larynx/wav/ipa_wavs.txt
larynx/wav/labial-palatal_approximant.wav
larynx/wav/labiodental_approximant.wav
larynx/wav/labiodental_nasal.wav
larynx/wav/mid-central_vowel.wav
larynx/wav/near-close_near-back_rounded_vowel.wav
larynx/wav/near-close_near-front_rounded_vowel.wav
