Metadata-Version: 2.1
Name: larynx
Version: 1.1.0
Summary: Neural text to speech system using the International Phonetic Alphabet
Home-page: https://github.com/rhasspy/larynx
Author: Michael Hansen
Author-email: mike@rhasspy.org
License: UNKNOWN
Platform: UNKNOWN
Classifier: Programming Language :: Python :: 3
Classifier: Programming Language :: Python :: 3.7
Classifier: Programming Language :: Python :: 3.8
Classifier: License :: OSI Approved :: MIT License
Requires-Python: >=3.7
